mex/__init__.py
mex/artificial/__init__.py
mex/artificial/helpers.py
mex/artificial/identity.py
mex/artificial/main.py
mex/artificial/provider.py
mex/artificial/types.py
mex/py.typed
mex_artificial-1.1.0.dist-info/METADATA
mex_artificial-1.1.0.dist-info/WHEEL
mex_artificial-1.1.0.dist-info/entry_points.txt
mex_artificial-1.1.0.dist-info/licenses/LICENSE
mex_artificial-1.1.0.dist-info/RECORD
