Metadata-Version: 2.1
Name: mex-artificial
Version: 1.1.0
Summary: Create artificial data for the MEx project.
Author-Email: MEx Team <mex@rki.de>
License: MIT License
Project-URL: Repository, https://github.com/robert-koch-institut/mex-artificial
Requires-Python: <3.12,>=3.11
Requires-Dist: annotated-types<=0.7
Requires-Dist: faker<38,>=37
Requires-Dist: mex-common<2,>=1.7
Requires-Dist: pydantic
Requires-Dist: typer>=0.19
Provides-Extra: dev
Requires-Dist: ipdb>=0.13; extra == "dev"
Requires-Dist: mypy>=1; extra == "dev"
Requires-Dist: pytest-cov>=6; extra == "dev"
Requires-Dist: pytest-random-order>=1; extra == "dev"
Requires-Dist: pytest-xdist>=3; extra == "dev"
Requires-Dist: pytest>=8; extra == "dev"
Requires-Dist: ruff>=0.14; extra == "dev"
Requires-Dist: sphinx>=8; extra == "dev"
